datacatalog_util/__init__.py
datacatalog_util/datacatalog_util_cli.py
datacatalog_util-0.11.6.dist-info/AUTHORS.rst
datacatalog_util-0.11.6.dist-info/LICENSE
datacatalog_util-0.11.6.dist-info/METADATA
datacatalog_util-0.11.6.dist-info/WHEEL
datacatalog_util-0.11.6.dist-info/entry_points.txt
datacatalog_util-0.11.6.dist-info/top_level.txt
datacatalog_util-0.11.6.dist-info/RECORD
