Metadata-Version: 2.1
Name: datacatalog-util
Version: 0.11.6
Summary: A package to manage Google Cloud Data Catalog helper commands and scripts
Home-page: https://github.com/mesmacosta/datacatalog-util
Author: Marcelo Miranda
Author-email: mesmacosta@gmail.com
License: MIT license
Platform: Posix; MacOS X; Windows
Classifier: Development Status :: 3 - Alpha
Classifier: Natural Language :: English
Classifier: Programming Language :: Python
Classifier: Programming Language :: Python :: 3.6
Classifier: Programming Language :: Python :: 3.7
Requires-Python: >=3.6
Requires-Dist: google-cloud-datacatalog (<2.0.0,>=1.0.0)
Requires-Dist: datacatalog-tag-manager (==2.0.5)
Requires-Dist: datacatalog-tag-exporter
Requires-Dist: datacatalog-fileset-enricher
Requires-Dist: datacatalog-fileset-processor (==0.1.4)
Requires-Dist: datacatalog-tag-template-processor (==0.1.2)
Requires-Dist: datacatalog-tag-template-exporter
Requires-Dist: datacatalog-fileset-exporter
Requires-Dist: datacatalog-object-storage-processor
